setup.cfg
setup.py
SdcStatsBot/__init__.py
SdcStatsBot/client.py
SdcStatsBot.egg-info/PKG-INFO
SdcStatsBot.egg-info/SOURCES.txt
SdcStatsBot.egg-info/dependency_links.txt
SdcStatsBot.egg-info/not-zip-safe
SdcStatsBot.egg-info/requires.txt
SdcStatsBot.egg-info/top_level.txt