Metadata-Version: 2.1
Name: SdcStatsBot
Version: 0.2.7
Summary: A Python wrapper for the SDC API
Home-page: https://github.com/masezev/SdcStatsBot
Author: Masezev
Author-email: csgomanagement1@gmail.com
Project-URL: Поддержка, https://discord.gg/H7FQFGEPz5
Keywords: A Python wrapper for the SDC API
Requires-Python: >=3.8.0
Requires-Dist: aiohttp
Requires-Dist: loguru
